LICENSE
minnwest_esb_client/__init__.py
minnwest_esb_client/api/__init__.py
minnwest_esb_client/api/account/__init__.py
minnwest_esb_client/api/account/post_api_v_1_q_2_account_account_transfer_view.py
minnwest_esb_client/api/account_action/__init__.py
minnwest_esb_client/api/account_action/post_api_v_1_q_2_account_action_e_statements.py
minnwest_esb_client/api/auth/__init__.py
minnwest_esb_client/api/auth/get_api_v_1_q_2_auth_check.py
minnwest_esb_client/api/auth/post_api_v_1_q_2_auth_login.py
minnwest_esb_client/api/auth/post_api_v_1_q_2_auth_refresh.py
minnwest_esb_client/api/test/__init__.py
minnwest_esb_client/api/test/get_api_v_1_q_2_test_get_host_addresses.py
minnwest_esb_client/api/test/get_api_v_1_q_2_test_ping.py
minnwest_esb_client/api/test/get_api_v_1_q_2_test_ping_env.py
minnwest_esb_client/api/test/get_api_v_1_q_2_test_ping_ibi.py
minnwest_esb_client/api/test/get_api_v_1_q_2_test_ping_prm1452.py
minnwest_esb_client/api/test/get_api_v_1_q_2_test_ping_sql.py
minnwest_esb_client/api/transfer/__init__.py
minnwest_esb_client/api/transfer/post_api_v_1_q_2_transfer_internal_transfer.py
minnwest_esb_client/api/users/__init__.py
minnwest_esb_client/api/users/get_api_v_1_q_2_users_get_current_user.py
minnwest_esb_client/client.py
minnwest_esb_client/errors.py
minnwest_esb_client/models/__init__.py
minnwest_esb_client/models/account_e_statement_enrollment.py
minnwest_esb_client/models/account_transfer_view_request.py
minnwest_esb_client/models/account_type.py
minnwest_esb_client/models/boolean_api_result.py
minnwest_esb_client/models/int_64_api_result.py
minnwest_esb_client/models/internal_transfer_request.py
minnwest_esb_client/models/login_model.py
minnwest_esb_client/models/problem_details.py
minnwest_esb_client/models/soa_account.py
minnwest_esb_client/models/soa_account_api_result.py
minnwest_esb_client/models/soa_transfer.py
minnwest_esb_client/models/token_model.py
minnwest_esb_client/models/token_model_api_result.py
minnwest_esb_client-1.0.1.dist-info/LICENSE
minnwest_esb_client-1.0.1.dist-info/METADATA
minnwest_esb_client-1.0.1.dist-info/WHEEL
minnwest_esb_client-1.0.1.dist-info/RECORD
